{"Ads": [
    {
      "select_main_ads": "ADMOB",
      "select_backup_ads":"FACEBOOK",
      "main_ads_banner": "ca-app-pub-4941185249786037/1446403480",
      "main_ads_intertitial":"ca-app-pub-4941185249786037/1901699053",
      "main_ads_natives":"null",
      "backup_ads_natives":"552410750119432_552417810118726",
      "backup_ads_banner":"552410750119432_552411030119404",
      "backup_ads_intertitial":"552410750119432_552417780118729",
      "open_ads_admob":"ca-app-pub-4941185249786037/9925925088",
      "open_ads_alien":"NULL",
      "switch_open_ads":"1",
      "switch_banner_natives_ads":"1",
      "on_off_native_listview":"1",
      "interval_intertitial": 1,
      "initialize_sdk":"1a4f57855",
      "initialize_sdk_backup_ads":"1a4f57855",
      "high_paying_keyword_1": "",
      "high_paying_keyword_2": "",
      "high_paying_keyword_3": "",
      "high_paying_keyword_4": "",
      "high_paying_keyword_5": "",
      "status_app": "0",
      "link_redirect": "https://"

    }
  ],
     "Categories": [
    {
      "category": "cny",
      "image_link": "https://frame.twibbonize.com/ae6e32c6-df6e-4f52-8020-4a9d4b4df321.png"
    }
  ],

  "Item": [
    {
      "id": 1,
      "category": "cny",
      "title": "Chinese New Year1",
      "image_link": "https://frame.twibbonize.com/ae6e32c6-df6e-4f52-8020-4a9d4b4df321.png"
    },
    {
      "id": 2,
      "category": "cny",
      "title": "Chinese New Year2",
      "image_link": "https://frame.twibbonize.com/3c7491df-9ed4-4ad0-a34e-6fc3e300753e.png"
    },
    {
      "id": 3,
      "category": "cny",
      "title": "Chinese New Year3",
      "image_link": "https://frame.twibbonize.com/c1f6fa7c-7544-4a9f-9c69-e10d66ed14ae.png"
    },
    {
      "id": 4,
      "category": "cny",
      "title": "Chinese New Year4",
      "image_link": "https://frame.twibbonize.com/0f339c04-a14a-4ccd-b475-a66193b9f371.png"
    },
    {
      "id": 5,
      "category": "cny",
      "title": "Chinese New Year5",
      "image_link": "https://frame.twibbonize.com/99576851-9ffe-4c42-bcde-93b1a5302f8f.png"
    },
    {
      "id": 6,
      "category": "cny",
      "title": "Chinese New Year6",
      "image_link": "https://frame.twibbonize.com/3b28c246-06f8-444a-a4a2-2e1af14c3340.png"
    },
    {
      "id": 7,
      "category": "cny",
      "title": "Chinese New Year7",
      "image_link": "https://frame.twibbonize.com/9c9b5e11-30ff-4c39-845f-4f8ffe8f4df9.png"
    },
	 {
      "id": 8,
      "category": "cny",
      "title": "Chinese Costume1",
      "image_link": "https://raw.githubusercontent.com/masutarji/gambar/main/cina1.webp"
    },
    {
      "id": 9,
      "category": "cny",
      "title": "Chinese Costume2",
      "image_link": "https://raw.githubusercontent.com/masutarji/gambar/main/cina1.webp"
    },
    {
      "id": 10,
      "category": "cny",
      "title": "Chinese Costume3",
      "image_link": "https://raw.githubusercontent.com/masutarji/gambar/main/cina1.webp"
    },
    {
      "id": 11,
      "category": "cny",
      "title": "Chinese Costume4",
      "image_link": "https://raw.githubusercontent.com/masutarji/gambar/main/cina1.webp"
    },
    {
      "id": 12,
      "category": "cny",
      "title": "Chinese Costume5",
      "image_link": "https://raw.githubusercontent.com/masutarji/gambar/main/cina1.webp"
    },
    {
      "id": 13,
      "category": "cny",
      "title": "Chinese Costume6",
      "image_link": "https://raw.githubusercontent.com/masutarji/gambar/main/cina1.webp"
    },
    {
      "id": 14,
      "category": "cny",
      "title": "Chinese Costume7",
      "image_link": "https://raw.githubusercontent.com/masutarji/gambar/main/cina1.webp"
    }
  ]
} 
