{"Ads": 
  [
    {
      "select_main_ads": "ALIEN-M",
      "select_backup_ads":"APPLOVIN-M",
      "main_ads_banner": "u5mxt9q5ddp69kfyo5ccwyghh20ge249",
      "main_ads_intertitial":"flq2gbka6j958jyrqhfzb5prd00e7mem",
      "main_ads_natives":"589fmqqpblgyhri1che42xcxnfrhnz5k",
      "backup_ads_natives":"0ebca3642565c790",
      "backup_ads_banner":"343868eedc99b435",
      "backup_ads_intertitial":"ccbfb0a22b969024",
      "open_ads_admob":"ca-app-pub-4941185249786037/5413524185",
      "open_ads_alien":"mbx0pc0opngzj383fiqugwcd2exadgn7",
      "open_ads_max":"0b5ae4fade3c16e1",
      "open_ads_wortise":"",
      "on_off_native_listview":"1",
      "interval_intertitial": 1,
      "initialize_sdk":"201968169",
      "initialize_sdk_backup_ads":"201968169",
      "high_paying_keyword_1": "",
      "high_paying_keyword_2": "",
      "high_paying_keyword_3": "",
      "high_paying_keyword_4": "",
      "high_paying_keyword_5": "",
      "status_app": "0",
      "link_redirect": "https://"

    }
  ],
     "Categories": [
    {
      "category": "Imlek",
      "image_link": "https://frame.twibbonize.com/14023273-5fd8-4e9c-9065-11dd8eba022c.png"

    }
  ],

  "Item": [
    {
      "id": 1,
      "category": "Imlek",
      "title": "CNY 1",
      "image_link": "https://frame.twibbonize.com/14023273-5fd8-4e9c-9065-11dd8eba022c.png"
    },
    {
      "id": 2,
      "category": "Imlek",
      "title": "CNY 2",
      "image_link": "https://frame.twibbonize.com/782e6f30-7446-49be-9d1d-57b80b432f93.png"
    },
    {
      "id": 3,
      "category": "Imlek",
      "title": "CNY 3",
      "image_link": "https://frame.twibbonize.com/8709ef75-63bf-434a-b9b2-da5f31d3cb3b.png"
    },
    {
      "id": 4,
      "category": "Imlek",
      "title": "CNY 4",
      "image_link": "https://frame.twibbonize.com/881fe23a-d6e0-4b07-bb54-4a189cdb9423.png"
    },
    {
      "id": 5,
      "category": "Imlek",
      "title": "CNY 5",
      "image_link": "https://frame.twibbonize.com/a4d9ea8b-d17c-40df-94d2-b4edfb9d547a.png"
    },
    {
      "id": 6,
      "category": "Imlek",
      "title": "CNY 6",
      "image_link": "https://frame.twibbonize.com/89899d04-e9a5-4d89-9232-d968832d7e35.png"
    },
    {
      "id": 7,
      "category": "Imlek",
      "title": "CNY 7",
      "image_link": "https://frame.twibbonize.com/7af177a1-e7c3-4fa2-a065-bf4b8170f8cc.png"
    },
    {
      "id": 8,
      "category": "Imlek",
      "title": "CNY 8",
      "image_link": "https://frame.twibbonize.com/c2e92bdf-8c36-4093-91c0-286b1e83ee7f.png"
    },
    {
      "id": 9,
      "category": "Imlek",
      "title": "CNY 9",
      "image_link": "https://frame.twibbonize.com/46ebfc99-08e6-4b5f-8f68-bb48dc9b5c69.png"
    },
    {
      "id": 10,
      "category": "Imlek",
      "title": "CNY 10",
      "image_link": "https://frame.twibbonize.com/09502b7d-d8fc-43ce-9a4f-d20d804265c6.png"
    }
  ]
}
